utilslz/__init__.py
utilslz/cli.py
psutilslz-1.1.dist-info/METADATA
psutilslz-1.1.dist-info/WHEEL
psutilslz-1.1.dist-info/entry_points.txt
psutilslz-1.1.dist-info/top_level.txt
psutilslz-1.1.dist-info/RECORD
