Metadata-Version: 2.4
Name: psutilslz
Version: 1.1
Summary: CLI utility to SSH file content and run v.py
Author: ubuntu
Requires-Python: >=3.6
Dynamic: author
Dynamic: requires-python
Dynamic: summary
